{
  "total_affected": 2508,
  "by_type": {
    "Passenger": 703,
    "Other": 109,
    "Crew": 1696
  },
  "by_gender": {
    "Male": 1662,
    "Female": 654,
    "Unknown": 184,
    "Not available - PCF": 8
  },
  "by_age_band": {
    "65+": 531,
    "Unknown": 592,
    "55-64": 336,
    "<25": 208,
    "25-34": 305,
    "45-54": 263,
    "35-44": 273
  },
  "by_injury_type": {
    "Bone fractures": 844,
    "Drowning and asphyxiation": 420,
    "Wounds and superficial injuries": 344,
    "Dislocations, sprains and strains": 311,
    "Concussions and internal injuries (including crush injuries not mentioned above)": 203,
    "Unknown or unspecified": 106,
    "Traumatic amputations (Loss of body parts)": 70,
    "Burns, scalds and frostbites": 61,
    "Multiple injuries": 35,
    "Other specified injuries not included under other headings": 22,
    "Effects of temperature extremes, light and radiation": 18,
    "Shock": 14,
    "Poisonings and infections": 13,
    "Not available - PCF": 8,
    "Effects of sound, vibration and pressure": 4
  },
  "by_body_part": {
    "Whole body and multiple sites -> Multiple sites of the body affected": 272,
    "Whole body and multiple sites -> Whole body (Systemic effects)": 263,
    "Lower Extremities -> Leg, including knee": 246,
    "Upper Extremities -> Finger(s)": 208,
    "Upper Extremities -> Arm, including elbow": 156,
    "Lower Extremities -> Ankle": 155,
    "Upper Extremities -> Shoulder and shoulder joints": 138,
    "Head -> Head (Caput), brain and cranial nerves and vessels": 126,
    "Back, including spine and vertebra in the back -> Back, including spine and vertebra in the back": 118,
    "Upper Extremities -> Hand": 110,
    "Upper Extremities -> Wrist": 106,
    "Lower Extremities -> Hip and hip joint": 80,
    "Lower Extremities -> Foot": 63,
    "Torso and organs -> Rib cage, ribs including joints and shoulder blade": 61,
    "Head -> Facial area": 59,
    "Not specified": 55,
    "Head -> Head, multiple sites affected": 45,
    "Torso and organs -> Chest area including organs": 39,
    "Head -> Eye(s)": 28,
    "Back, including spine and vertebra in the back -> Back, other parts not mentioned above": 25
  },
  "ppe_used_pct": 0.0,
  "ppe_deficient_pct": 0.0,
  "on_duty_pct": 0.0
}